{
  "module_name": "secure_shell_service_secure_executor",
  "module_type": "single_file",
  "confidence_score": 0.9,
  "files": [
    "src/secure_shell_service/secure_executor.py"
  ],
  "file_count": 1,
  "total_lines": 369,
  "total_classes": 2,
  "total_functions": 1,
  "total_imports": 7,
  "module_docstring": "\"\"\"\nsecure_shell_service_secure_executor\n\nPurpose: Service layer and API endpoints\nGraph API Level: 1\nProjection System: service_system\n\nModule Type: single_file\nFiles: 1\nTotal Lines: 369\nClasses: 2\nFunctions: 1\nImports: 7\n\nThis module was automatically detected and modeled by the Enhanced Module Modeling System.\n\"\"\"",
  "module_purpose": "Service layer and API endpoints",
  "graph_api_level": "1",
  "projection_system": "service_system",
  "all_classes": [],
  "all_functions": [],
  "all_imports": [],
  "dependencies": [],
  "class_dependencies": {},
  "function_dependencies": {},
  "module_structure": {
    "module_info": {
      "name": "secure_shell_service_secure_executor",
      "type": "single_file",
      "confidence": 0.9,
      "file_count": 1
    },
    "metrics": {
      "total_lines": 369,
      "total_classes": 2,
      "total_functions": 1,
      "total_imports": 7
    },
    "files": [
      {
        "path": "src/secure_shell_service/secure_executor.py",
        "name": "secure_executor.py",
        "stem": "secure_executor"
      }
    ],
    "aggregated_content": {
      "classes": [],
      "functions": [],
      "imports": []
    }
  },
  "creation_timestamp": "2025-08-16T10:42:18.794418",
  "version": "1.0.0"
}